Workbook

Sheet Hypothèses Clés
A1: HYPOTHESES CLES
A4: Année 1 | E4: Année 2 | H4: Année 3 | K4: Année 4 | N4: Année 5
A5: Paramètre | B5: Pessimiste | C5: Réaliste | D5: Optimiste | E5: Pessimiste | F5: Réaliste | G5: Optimiste | H5: Pessimiste | I5: Réaliste | J5: Optimiste | K5: Pessimiste | L5: Réaliste | M5: Optimiste | N5: Pessimiste | O5: Réaliste | P5: Optimiste
A6: Coachs Année 1 | B6: 300 | C6: 500 | D6: 800 | E6: =B6+(B6*B10) -> 330 | F6: =C6+(C6*C10) -> 625 | G6: =D6+(D6*D10) -> 1120 | H6: =E6+(E6*E10) -> 363 | I6: =F6+(F6*C10) -> 781.25 | J6: =G6+(G6*D10) -> 1568 | K6: =H6+(H6*H10) -> 399.3 | L6: =I6+(I6*C10) -> 976.5625 | M6: =J6+(J6*D10) -> 2195.2 | N6: =K6+(K6*K10) -> 439.23 | O6: =L6+(L6*C10) -> 1220.7031 | P6: =M6+(M6*D10) -> 3073.28
A7: Coachs Premium année 1 (ne pas modifier) | B7: =B6*B12 -> 180 | C7: =C6*C12 -> 300 | D7: =D6*D12 -> 480 | E7: =E6*E12 -> 198 | F7: =F6*F12 -> 375 | G7: =G6*G12 -> 672 | H7: =H6*H12 -> 217.8 | I7: =I6*I12 -> 468.75 | ... P7: =P6*P12 -> 1843.968
A8: Coach Non premium Année 1 (ne pas modifier) | B8: =B6-B7 -> 120 | C8: =C6-C7 -> 200 | D8: =D6-D7 -> 320 | E8: =E6-E7 -> 132 | F8: =F6-F7 -> 250 | G8: =G6-G7 -> 448 | H8: =H6-H7 -> 145.2 | I8: =I6-I7 -> 312.5 | ... P8: =P6-P7 -> 1229.312
A9: Clubs Année 1 | B9: 50 | C9: 100 | D9: 150 | E9: =B9+(B9*B11) -> 55 | F9: =C9+(C9*C11) -> 130 | G9: =D9+(D9*D11) -> 225 | H9: =E9+(E9*E11) -> 60.5 | I9: =F9+(F9*C11) -> 169 | J9: =G9+(G9*D11) -> 337.5 | K9: =H9+(H9*H11) -> 66.55 | L9: =I9+(I9*C11) -> 219.7 | M9: =J9+(J9*D11) -> 506.25 | N9: =K9+(K9*K11) -> 73.205 | O9: =L9+(L9*C11) -> 285.61 | P9: =M9+(M9*D11) -> 759.375
A10: Croissance coachs (%) | B10: 0.1 | C10: 0.25 | D10: 0.4 | E10: 0.1 | F10: 0.25 | G10: 0.4 | H10: 0.1 | I10: 0.25 | J10: 0.4 | K10: 0.1 | L10: 0.25 | M10: 0.4 | N10: 0.1 | O10: 0.25 | P10: 0.4
A11: Croissance clubs (%) | B11: 0.1 | C11: 0.3 | D11: 0.5 | E11: 0.1 | F11: 0.3 | G11: 0.5 | H11: 0.1 | I11: 0.3 | J11: 0.5 | K11: 0.1 | L11: 0.3 | M11: 0.5 | N11: 0.1 | O11: 0.3 | P11: 0.5
A12: Ratio premium (%) | B12: 0.6 | C12: 0.6 | D12: 0.6 | E12: 0.6 | F12: 0.6 | G12: 0.6 | H12: 0.6 | I12: 0.6 | J12: 0.6 | K12: 0.6 | L12: 0.6 | M12: 0.6 | N12: 0.6 | O12: 0.6 | P12: 0.6
A13: Prix séance (€) | B13: 30 | C13: 30 | D13: 30 | E13: 30 | F13: 30 | G13: 30 | H13: 30 | I13: 30 | J13: 30 | K13: 30 | L13: 30 | M13: 30 | N13: 30 | O13: 30 | P13: 30
A14: Prix abonnement Premium Coach (€) | B14: 19.99 | C14: 19.99 | D14: 19.99 | E14: 19.99 | F14: 19.99 | G14: 19.99 | H14: 19.99 | I14: 19.99 | J14: 19.99 | K14: 19.99 | L14: 19.99 | M14: 19.99 | N14: 19.99 | O14: 19.99 | P14: 19.99
A15: Prix abonnement Club | B15: 29.99 | C15: 29.99 | D15: 29.99 | E15: 29.99 | F15: 29.99 | G15: 29.99 | H15: 29.99 | I15: 29.99 | J15: 29.99 | K15: 29.99 | L15: 29.99 | M15: 29.99 | N15: 29.99 | O15: 29.99 | P15: 29.99
A16: Prix moyen contenu | B16: 30 | C16: 30 | D16: 30 | E16: 30 | F16: 30 | G16: 30 | H16: 30 | I16: 30 | J16: 30 | K16: 30 | L16: 30 | M16: 30 | N16: 30 | O16: 30 | P16: 30
A17: Prix moyen abonnement contenu coach | B17: 8.99 | C17: 8.99 | D17: 8.99 | E17: 8.99 | F17: 8.99 | G17: 8.99 | H17: 8.99 | I17: 8.99 | J17: 8.99 | K17: 8.99 | L17: 8.99 | M17: 8.99 | N17: 8.99 | O17: 8.99 | P17: 8.99
A18: Commission séances (%) | B18: 0.15 | C18: 0.15 | D18: 0.15 | E18: 0.15 | F18: 0.15 | G18: 0.15 | H18: 0.15 | I18: 0.15 | J18: 0.15 | K18: 0.15 | L18: 0.15 | M18: 0.15 | N18: 0.15 | O18: 0.15 | P18: 0.15
A19: Commission ventes contenu (%) | B19: 0.2 | C19: 0.2 | D19: 0.2 | E19: 0.2 | F19: 0.2 | G19: 0.2 | H19: 0.2 | I19: 0.2 | J19: 0.2 | K19: 0.2 | L19: 0.2 | M19: 0.2 | N19: 0.2 | O19: 0.2 | P19: 0.2
A20: Comission Abonnement coach | B20: 0.2 | C20: 0.2 | D20: 0.2 | E20: 0.2 | F20: 0.2 | G20: 0.2 | H20: 0.2 | I20: 0.2 | J20: 0.2 | K20: 0.2 | L20: 0.2 | M20: 0.2 | N20: 0.2 | O20: 0.2 | P20: 0.2
A21: Nombre de réservation/coach/mois | B21: 4 | C21: 4 | D21: 4 | E21: 4 | F21: 4 | G21: 4 | H21: 4 | I21: 4 | J21: 4 | K21: 4 | L21: 4 | M21: 4 | N21: 4 | O21: 4 | P21: 4
... A23: Nombre d'abonné par coach | B23: 0 | C23: 10 | D23: 20 | E23: 0 | F23: 10 | G23: 20 | H23: 0 | I23: 10 | J23: 20 | K23: 0 | L23: 10 | M23: 20 | N23: 0 | O23: 10 | P23: 20

Sheet Charges Opérationnelles
A1: CHARGES OPERATIONNELLES
A2: Poste | B2: Année 1 | C2: Année 2 | D2: Année 3 | E2: Année 4 | F2: Année 5
A3: Développement plateforme | B3: 12000
A4: Maintenance technique
A5: Infrastructure | B5: 2000 | C5: =B5+(B5*B16) -> 2500 | D5: =C5+(C5*C16) -> 3125 | E5: =D5+(D5*D16) -> 3906.25 | F5: =E5+(E5*E16) -> 4882.8125
A6: Marketing / Communication | B6: 20000 | C6: =B6+(B6*B16) -> 25000 | D6: =C6+(C6*C16) -> 31250 | E6: =D6+(D6*D16) -> 39062.5 | F6: =E6+(E6*E16) -> 48828.125
A7: Événements Partenariats | B7: 5000 | C7: =B7+(B7*B16) -> 6250 | D7: =C7+(C7*C16) -> 7812.5 | E7: =D7+(D7*D16) -> 9765.625 | F7: =E7+(E7*E16) -> 12207.031
A8: Juridique RGPD | B8: 4000 | C8: 1500 | D8: 1500 | E8: 1500 | F8: 1500
A9: Comptabilité | B9: 0 | C9: 1500 | D9: 1500 | E9: 1500 | F9: 1500
A10: Assurance | B10: 1800 | C10: 2100 | D10: 2400 | E10: 2700 | F10: 3000
A11: API Services | B11: 2000 | C11: =B11+(B11*B16) -> 2500 | D11: =C11+(C11*C16) -> 3125 | E11: =D11+(D11*D16) -> 3906.25 | F11: =E11+(E11*E16) -> 4882.8125
A12: Outils SaaS | B12: 1200 | C12: =B12+(B12*B16) -> 1500 | D12: =C12+(C12*C16) -> 1875 | E12: =D12+(D12*D16) -> 2343.75 | F12: =E12+(E12*E16) -> 2929.6875
A13: Serveurs Backup | B13: 750 | C13: =B13+(B13*B16) -> 937.5 | D13: =C13+(C13*C16) -> 1171.875 | E13: =D13+(D13*D16) -> 1464.8438 | F13: =E13+(E13*E16) -> 1831.0547
A14: Ressources (stagiaire) | B14: 7200 | C14: 7200 | D14: 7200 | E14: 7200 | F14: 7200
A15: Contingences (5%) | B15: =(B3+B4+B5+B6+B7+B8+B9+B10+B11+B12+B13+B14)*5% -> 2797.5 | C15: =(C3+C4+C5+C6+C7+C8+C9+C10+C11+C12+C13+C14)*5% -> 2549.375 | D15: =(D3+D4+D5+D6+D7+D8+D9+D10+D11+D12+D13+D14)*5% -> 3047.9688 | E15: =(E3+E4+E5+E6+E7+E8+E9+E10+E11+E12+E13+E14)*5% -> 3667.4609 | F15: =(F3+F4+F5+F6+F7+F8+F9+F10+F11+F12+F13+F14)*5% -> 4438.0762
A16: Taux de croissance des charges 25% (hors dev, compta, juriste,stagiaire) | B16: ='Hypothèses Clés'!C10 -> 0.25 | C16: ='Hypothèses Clés'!F10 -> 0.25 | D16: ='Hypothèses Clés'!I10 -> 0.25 | E16: ='Hypothèses Clés'!L10 -> 0.25 | F16: ='Hypothèses Clés'!O10 -> 0.25
A17: TOTAL CHARGES | B17: =SUM(B3:B16) -> 58747.75 | C17: =SUM(C3:C16) -> 53537.125 | D17: =SUM(D3:D16) -> 64007.594 | E17: =SUM(E3:E16) -> 77016.93 | F17: =SUM(F3:F16) -> 93199.85
A19: Maintenance technique = débeugage, entretiens, MAJ
A20: Infrastructure = hébergement, serveur, base de données
A21: API service = google API + stockage vidéo, photos, pdf, Carte d'identité etc.. COÛT = 0.02 ct / giga - ref =10GO / coach + rappel notif
A22: Serveur backup = copie de secours des données et de la plateforme
A23: Contingence = Réserve en cas de problème

Sheet Scénario Pessimiste
A1: SCENARIO PESSIMISTE - Croissance: Coachs +10%, Clubs +10%
B2: Année 1 | C2: Année 2 | D2: Année 3 | E2: Année 4 | F2: Année 5
A3: REVENUS
A4: Commission séances / an | B4: ='Hypothèses Clés'!B8*'Hypothèses Clés'!B21*'Hypothèses Clés'!B13*'Hypothèses Clés'!B18*12 -> 25920 | C4: ='Hypothèses Clés'!E8*'Hypothèses Clés'!E21*'Hypothèses Clés'!E13*'Hypothèses Clés'!E18*12 -> 28512 | D4: ='Hypothèses Clés'!H8*'Hypothèses Clés'!H21*'Hypothèses Clés'!H13*'Hypothèses Clés'!H18*12 -> 31363.2 | E4: ='Hypothèses Clés'!K8*'Hypothèses Clés'!K21*'Hypothèses Clés'!K13*'Hypothèses Clés'!K18*12 -> 34499.52 | F4: ='Hypothèses Clés'!N8*'Hypothèses Clés'!N21*'Hypothèses Clés'!N13*'Hypothèses Clés'!N18*12 -> 37949.472
A5: Abonnement coachs premium / an | B5: ='Hypothèses Clés'!B7*'Hypothèses Clés'!B14*12 -> 43178.4 | C5: ='Hypothèses Clés'!E7*'Hypothèses Clés'!E14*12 -> 47496.24 | D5: ='Hypothèses Clés'!H7*'Hypothèses Clés'!H14*12 -> 52245.864 | E5: ='Hypothèses Clés'!K7*'Hypothèses Clés'!K14*12 -> 57470.45 | F5: ='Hypothèses Clés'!N7*'Hypothèses Clés'!N14*12 -> 63217.495
A6: Abonnement clubs premium / an | B6: ='Hypothèses Clés'!B9*'Hypothèses Clés'!B15*12 -> 17994 | C6: ='Hypothèses Clés'!E9*'Hypothèses Clés'!E15*12 -> 19793.4 | D6: ='Hypothèses Clés'!H9*'Hypothèses Clés'!H15*12 -> 21772.74 | E6: ='Hypothèses Clés'!K9*'Hypothèses Clés'!K15*12 -> 23950.014 | F6: ='Hypothèses Clés'!N9*'Hypothèses Clés'!N15*12 -> 26345.015
A7: Ventes contenu / an | B7: ='Hypothèses Clés'!B7*'Hypothèses Clés'!B22*'Hypothèses Clés'!B16*'Hypothèses Clés'!B19*12 -> 25920 | C7: ='Hypothèses Clés'!E7*'Hypothèses Clés'!E22*'Hypothèses Clés'!E16*'Hypothèses Clés'!E19*12 -> 28512 | D7: ='Hypothèses Clés'!H7*'Hypothèses Clés'!H22*'Hypothèses Clés'!H16*'Hypothèses Clés'!H19*12 -> 31363.2 | E7: ='Hypothèses Clés'!K7*'Hypothèses Clés'!K22*'Hypothèses Clés'!K16*'Hypothèses Clés'!K19*12 -> 34499.52 | F7: ='Hypothèses Clés'!N7*'Hypothèses Clés'!N22*'Hypothèses Clés'!N16*'Hypothèses Clés'!N19*12 -> 37949.472
A8: Abonnement contenu / an | B8: ='Hypothèses Clés'!B7*'Hypothèses Clés'!B23*'Hypothèses Clés'!B17*'Hypothèses Clés'!B20*12 -> 0 | C8: ='Hypothèses Clés'!E7*'Hypothèses Clés'!E23*'Hypothèses Clés'!E17*'Hypothèses Clés'!E20*12 -> 0 | D8: ='Hypothèses Clés'!H7*'Hypothèses Clés'!H23*'Hypothèses Clés'!H17*'Hypothèses Clés'!H20*12 -> 0 | E8: ='Hypothèses Clés'!K7*'Hypothèses Clés'!K23*'Hypothèses Clés'!K17*'Hypothèses Clés'!K20*12 -> 0 | F8: ='Hypothèses Clés'!N7*'Hypothèses Clés'!N23*'Hypothèses Clés'!N17*'Hypothèses Clés'!N20*12 -> 0
A9: TOTAL REVENUS par mois TTC | B9: =(B4+B5+B6+B7+B8)/12/1.2 -> 7848.0833 | C9: =(C4+C5+C6+C7+C8)/12/1.2 -> 8632.8917 | D9: =(D4+D5+D6+D7+D8)/12/1.2 -> 9496.1808 | E9: =(E4+E5+E6+E7+E8)/12/1.2 -> 10445.799 | F9: =(F4+F5+F6+F7+F8)/12/1.2 -> 11490.379
A10: TOTAL REVENUS par année TTC (TVA 20%) | B10: =SUM(B3:B8)/1.2 -> 94177 | C10: =SUM(C3:C8)/1.2 -> 103594.7 | D10: =SUM(D3:D8)/1.2 -> 113954.17 | E10: =SUM(E3:E8)/1.2 -> 125349.59 | F10: =SUM(F3:F8)/1.2 -> 137884.55
A12: CHARGES
A13: Charges opérationnelles | B13: ='Charges Opérationnelles'!B17 -> 58747.75 | C13: ='Charges Opérationnelles'!C17 -> 53537.125 | D13: ='Charges Opérationnelles'!D17 -> 64007.594 | E13: ='Charges Opérationnelles'!E17 -> 77016.93 | F13: ='Charges Opérationnelles'!F17 -> 93199.85
A14: Charges Stripe (2€/user) | B14: =('Hypothèses Clés'!C6+'Hypothèses Clés'!C9)*2*12 -> 14400 | C14: =('Hypothèses Clés'!F6+'Hypothèses Clés'!F9)*2*12 -> 18120 | D14: =('Hypothèses Clés'!I6+'Hypothèses Clés'!I9)*2*12 -> 22806 | E14: =('Hypothèses Clés'!L6+'Hypothèses Clés'!L9)*2*12 -> 28710.3 | F14: =('Hypothèses Clés'!O6+'Hypothèses Clés'!O9)*2*12 -> 36151.515
A15: TOTAL CHARGES | B15: =SUM(B13:B14) -> 73147.75 | C15: =SUM(C13:C14) -> 71657.125 | D15: =SUM(D13:D14) -> 86813.594 | E15: =SUM(E13:E14) -> 105727.23 | F15: =SUM(F13:F14) -> 129351.36
A17: EBITDA | B17: =B10-B15 -> 21029.25 | C17: =C10-C15 -> 31937.575 | D17: =D10-D15 -> 27140.576 | E17: =E10-E15 -> 19622.357 | F17: =F10-F15 -> 8533.1811
A18: Marge EBITDA (%) | B18: =(B17/B10)*100 -> 22.329497 | C18: =(C17/C10)*100 -> 30.829352 | D18: =(D17/D10)*100 -> 23.817098 | E18: =(E17/E10)*100 -> 15.654106 | F18: =(F17/F10)*100 -> 6.1886421
A19: Amortissements | B19: 1500 | C19: 2000 | D19: 2500 | E19: 3000 | F19: 3500
A20: EBIT | B20: =B10-B15-B19 -> 19529.25 | C20: =C10-C13-C19 -> 48057.575 | D20: =D10-D13-D19 -> 47446.576 | E20: =E10-E13-E19 -> 45332.657 | F20: =F10-F13-F19 -> 41184.696
A22: Remboursement crédit bancaire | B22: 0 | C22: =E35 -> 14700 | D22: =E36 -> 14160 | E22: =E37 -> 13620 | F22: =E38 -> 13080
A23: Résultat avant impôt | B23: =B10-B15-B19-B22 -> 19529.25 | C23: =C10-C15-C19-C22 -> 15237.575 | D23: =D10-D15-D19-D22 -> 10480.576 | E23: =E10-E15-E19-E22 -> 3002.3573 | F23: =F10-F15-F19-F22 -> -8046.8189
A24: Impôt (25%) | B24: =B23*0.25 -> 4882.3125 | C24: =C23*0.25 -> 3809.3938 | D24: =D23*0.25 -> 2620.1441 | E24: =E23*0.25 -> 750.58933 | F24: =F23*0.25 -> -2011.7047
A25: RESULTAT NET | B25: =B23-B24 -> 14646.938 | C25: =C23*1.25 -> 19046.969 | D25: =D23*1.25 -> 13100.72 | E25: =E23-E24 -> 2251.768 | F25: =F23-(F23*25%) -> -6035.1142
A26: Marge nette (%) | B26: =(B25/B10)*100 -> 15.552563 | C26: =(C25/C10)*100 -> 18.386046 | D26: =(D25/D10)*100 -> 11.496482 | E26: =(E25/E10)*100 -> 1.7963904 | F26: =(F25/F10)*100 -> -4.376933
A30: Montant emprunté | B30: 60000
A31: Taux d'emprunt | B31: 0.045
A32: Nombre d'année de remboursement | B32: 5
A34: Année | B34: Capital remboursé (€) | C34: Intérêts (%) | D34: Intérêts (€) | E34: Annuité | F34: Solde restant
A35: 1 | B35: =B30/B32 -> 12000 | C35: 0.045 | D35: =B30*B31 -> 2700 | E35: =B35+D35 -> 14700 | F35: =B30-B35 -> 48000
A36: 2 | B36: =B30/B32 -> 12000 | C36: 0.045 | D36: =F35*C36 -> 2160 | E36: =B36+D36 -> 14160 | F36: =F35-B36 -> 36000
A37: 3 | B37: =B30/B32 -> 12000 | C37: 0.045 | D37: =F36*C37 -> 1620 | E37: =B37+D37 -> 13620 | F37: =F36-B37 -> 24000
A38: 4 | B38: 12000 | C38: 0.045 | D38: =F37*C38 -> 1080 | E38: =B38+D38 -> 13080 | F38: =F37-B38 -> 12000
A39: 5 | B39: 12000 | C39: 0.045 | D39: =F38*C39 -> 540 | E39: =B39+D39 -> 12540 | F39: =F38-B39 -> 0

Sheet Scénario Réaliste
A1: SCENARIO REALISTE - Croissance: Coachs +25%, Clubs +30%
B2: Année 1 | C2: Année 2 | D2: Année 3 | E2: Année 4 | F2: Année 5
A3: REVENUS
A4: Commission séances / an | B4: ='Hypothèses Clés'!C8*'Hypothèses Clés'!C21*'Hypothèses Clés'!C13*'Hypothèses Clés'!C18*12 -> 43200 | C4: ='Hypothèses Clés'!F8*'Hypothèses Clés'!F21*'Hypothèses Clés'!F13*'Hypothèses Clés'!F18*12 -> 54000 | D4: ='Hypothèses Clés'!I8*'Hypothèses Clés'!I21*'Hypothèses Clés'!I13*'Hypothèses Clés'!I18*12 -> 67500 | E4: ='Hypothèses Clés'!L8*'Hypothèses Clés'!L21*'Hypothèses Clés'!L13*'Hypothèses Clés'!L18*12 -> 84375 | F4: ='Hypothèses Clés'!O8*'Hypothèses Clés'!O21*'Hypothèses Clés'!O13*'Hypothèses Clés'!O18*12 -> 105468.75
A5: Abonnement coachs premium / an | B5: ='Hypothèses Clés'!C7*'Hypothèses Clés'!C14*12 -> 71964 | C5: ='Hypothèses Clés'!F7*'Hypothèses Clés'!F14*12 -> 89955 | D5: ='Hypothèses Clés'!I7*'Hypothèses Clés'!I14*12 -> 112443.75 | E5: ='Hypothèses Clés'!L7*'Hypothèses Clés'!L14*12 -> 140554.69 | F5: ='Hypothèses Clés'!O7*'Hypothèses Clés'!O14*12 -> 175693.36
A6: Abonnement clubs premium / an | B6: ='Hypothèses Clés'!C9*'Hypothèses Clés'!C15*12 -> 35988 | C6: ='Hypothèses Clés'!F9*'Hypothèses Clés'!F15*12 -> 46784.4 | D6: ='Hypothèses Clés'!I9*'Hypothèses Clés'!I15*12 -> 60819.72 | E6: ='Hypothèses Clés'!L9*'Hypothèses Clés'!L15*12 -> 79065.636 | F6: ='Hypothèses Clés'!O9*'Hypothèses Clés'!O15*12 -> 102785.33
A7: Ventes contenu / an | B7: ='Hypothèses Clés'!C7*'Hypothèses Clés'!C22*'Hypothèses Clés'!C16*'Hypothèses Clés'!C19*12 -> 108000 | C7: ='Hypothèses Clés'!F7*'Hypothèses Clés'!F22*'Hypothèses Clés'!F16*'Hypothèses Clés'!F19*12 -> 135000 | D7: ='Hypothèses Clés'!I7*'Hypothèses Clés'!I22*'Hypothèses Clés'!I16*'Hypothèses Clés'!I19*12 -> 168750 | E7: ='Hypothèses Clés'!L7*'Hypothèses Clés'!L22*'Hypothèses Clés'!L16*'Hypothèses Clés'!L19*12 -> 210937.5 | F7: ='Hypothèses Clés'!O7*'Hypothèses Clés'!O22*'Hypothèses Clés'!O16*'Hypothèses Clés'!O19*12 -> 263671.88
A8: Abonnement contenu / an | B8: ='Hypothèses Clés'!C7*'Hypothèses Clés'!C23*'Hypothèses Clés'!C17*'Hypothèses Clés'!C20*12 -> 64728 | C8: ='Hypothèses Clés'!F7*'Hypothèses Clés'!F23*'Hypothèses Clés'!F17*'Hypothèses Clés'!F20*12 -> 80910 | D8: ='Hypothèses Clés'!I7*'Hypothèses Clés'!I23*'Hypothèses Clés'!I17*'Hypothèses Clés'!I20*12 -> 101137.5 | E8: ='Hypothèses Clés'!L7*'Hypothèses Clés'!L23*'Hypothèses Clés'!L17*'Hypothèses Clés'!L20*12 -> 126421.88 | F8: ='Hypothèses Clés'!O7*'Hypothèses Clés'!O23*'Hypothèses Clés'!O17*'Hypothèses Clés'!O20*12 -> 158027.34
A9: TOTAL REVENUS par mois | B9: =(B4+B5+B6+B7+B8)/12/1.2 -> 22491.667 | C9: =(C4+C5+C6+C7+C8)/12/1.2 -> 28239.542 | D9: =(D4+D5+D6+D7+D8)/12/1.2 -> 35461.873 | E9: =(E4+E5+E6+E7+E8)/12/1.2 -> 44538.521 | F9: =(F4+F5+F6+F7+F8)/12/1.2 -> 55947.684
A10: TOTAL REVENUS par année TTC (TVA 20%) | B10: =SUM(B3:B8)/1.2 -> 269900 | C10: =SUM(C3:C8)/1.2 -> 338874.5 | D10: =SUM(D3:D8)/1.2 -> 425542.47 | E10: =SUM(E3:E8)/1.2 -> 534462.25 | F10: =SUM(F3:F8)/1.2 -> 671372.21
A12: CHARGES
A13: Charges opérationnelles | B13: ='Charges Opérationnelles'!B17 -> 58747.75 | C13: ='Charges Opérationnelles'!C17 -> 53537.125 | D13: ='Charges Opérationnelles'!D17 -> 64007.594 | E13: ='Charges Opérationnelles'!E17 -> 77016.93 | F13: ='Charges Opérationnelles'!F17 -> 93199.85
A14: Charges Stripe (2€/user) | B14: =('Hypothèses Clés'!C6+'Hypothèses Clés'!C9)*2*12 -> 14400 | C14: =('Hypothèses Clés'!F6+'Hypothèses Clés'!F9)*2*12 -> 18120 | D14: =('Hypothèses Clés'!I6+'Hypothèses Clés'!I9)*2*12 -> 22806 | E14: =('Hypothèses Clés'!L6+'Hypothèses Clés'!L9)*2*12 -> 28710.3 | F14: =('Hypothèses Clés'!O6+'Hypothèses Clés'!O9)*2*12 -> 36151.515
A15: TOTAL CHARGES | B15: =SUM(B13:B14) -> 73147.75 | C15: =SUM(C13:C14) -> 71657.125 | D15: =SUM(D13:D14) -> 86813.594 | E15: =SUM(E13:E14) -> 105727.23 | F15: =SUM(F13:F14) -> 129351.36
A17: EBITDA | B17: =B10-B15 -> 196752.25 | C17: =C10-C15 -> 267217.38 | D17: =D10-D15 -> 338728.88 | E17: =E10-E15 -> 428735.02 | F17: =F10-F15 -> 542020.85
A18: Marge EBITDA (%) | B18: =(B17/B10)*100 -> 72.898203 | C18: =(C17/C10)*100 -> 78.854377 | D18: =(D17/D10)*100 -> 79.599312 | E18: =(E17/E10)*100 -> 80.218017 | F18: =(F17/F10)*100 -> 80.733286
A19: Amortissements | B19: 1500 | C19: 2000 | D19: 2500 | E19: 3000 | F19: 3500
A20: EBIT | B20: =B10-B15-B19 -> 195252.25 | C20: =C10-C13-C19 -> 283337.38 | D20: =D10-D13-D19 -> 359034.88 | E20: =E10-E13-E19 -> 454445.32 | F20: =F10-F13-F19 -> 574672.36
A22: Remboursement crédit bancaire | B22: 0 | C22: =E35 -> 14700 | D22: =E36 -> 14160 | E22: =E37 -> 13620 | F22: =E38 -> 13080
A23: Résultat avant impôt | B23: =B10-B15-B19-B22 -> 195252.25 | C23: =C10-C15-C19-C22 -> 250517.38 | D23: =D10-D15-D19-D22 -> 322068.88 | E23: =E10-E15-E19-E22 -> 412115.02 | F23: =F10-F15-F19-F22 -> 525440.85
A24: Impôt (25%) | B24: =B23*0.25 -> 48813.062 | C24: =C23*0.25 -> 62629.344 | D24: =D23*0.25 -> 80517.22 | E24: =E23*0.25 -> 103028.75 | F24: =F23*0.25 -> 131360.21
A25: RESULTAT NET | B25: =B23-B24 -> 146439.19 | C25: =C23-C24 -> 187888.03 | D25: =D23-D24 -> 241551.66 | E25: =E23-E24 -> 309086.26 | F25: =F23-F24 -> 394080.64
A26: Marge nette (%) | B26: =(B25/B10)*100 -> 54.256831 | C26: =(C25/C10)*100 -> 55.444724 | D26: =(D25/D10)*100 -> 56.763232 | E26: =(E25/E10)*100 -> 57.831262 | F26: =(F25/F10)*100 -> 58.697788
A30: Montant emprunté | B30: 60000
A31: Taux d'emprunt | B31: 0.045
A32: Nombre d'année de remboursement | B32: 5
A34: Année | B34: Capital remboursé (€) | C34: Intérêts (%) | D34: Intérêts (€) | E34: Annuité | F34: Solde restant
A35: 1 | B35: =B30/B32 -> 12000 | C35: 0.045 | D35: =B30*B31 -> 2700 | E35: =B35+D35 -> 14700 | F35: =B30-B35 -> 48000
A36: 2 | B36: =B30/B32 -> 12000 | C36: 0.045 | D36: =F35*C36 -> 2160 | E36: =B36+D36 -> 14160 | F36: =F35-B36 -> 36000
A37: 3 | B37: =B30/B32 -> 12000 | C37: 0.045 | D37: =F36*C37 -> 1620 | E37: =B37+D37 -> 13620 | F37: =F36-B37 -> 24000
A38: 4 | B38: 12000 | C38: 0.045 | D38: =F37*C38 -> 1080 | E38: =B38+D38 -> 13080 | F38: =F37-B38 -> 12000
A39: 5 | B39: 12000 | C39: 0.045 | D39: =F38*C39 -> 540 | E39: =B39+D39 -> 12540 | F39: =F38-B39 -> 0

Sheet Scénario Optimiste
A1: SCENARIO OPTIMISTE - Croissance: Coachs +40%, Clubs +50%
B2: Année 1 | C2: Année 2 | D2: Année 3 | E2: Année 4 | F2: Année 5
A3: REVENUS
A4: Commission séances / an | B4: ='Hypothèses Clés'!D8*'Hypothèses Clés'!D21*'Hypothèses Clés'!D13*'Hypothèses Clés'!D18*12 -> 69120 | C4: ='Hypothèses Clés'!G8*'Hypothèses Clés'!G21*'Hypothèses Clés'!G13*'Hypothèses Clés'!G18*12 -> 96768 | D4: ='Hypothèses Clés'!J8*'Hypothèses Clés'!J21*'Hypothèses Clés'!J13*'Hypothèses Clés'!J18*12 -> 135475.2 | E4: ='Hypothèses Clés'!M8*'Hypothèses Clés'!M21*'Hypothèses Clés'!M13*'Hypothèses Clés'!M18*12 -> 189665.28 | F4: ='Hypothèses Clés'!P8*'Hypothèses Clés'!P21*'Hypothèses Clés'!P13*'Hypothèses Clés'!P18*12 -> 265531.39
A5: Abonnement coachs premium / an | B5: ='Hypothèses Clés'!D7*'Hypothèses Clés'!D14*12 -> 115142.4 | C5: ='Hypothèses Clés'!G7*'Hypothèses Clés'!G14*12 -> 161199.36 | D5: ='Hypothèses Clés'!J7*'Hypothèses Clés'!J14*12 -> 225679.1 | E5: ='Hypothèses Clés'!M7*'Hypothèses Clés'!M14*12 -> 315950.75 | F5: ='Hypothèses Clés'!P7*'Hypothèses Clés'!P14*12 -> 442331.04
A6: Abonnement clubs premium / an | B6: ='Hypothèses Clés'!D9*'Hypothèses Clés'!D15*12 -> 53982 | C6: ='Hypothèses Clés'!G9*'Hypothèses Clés'!G15*12 -> 80973 | D6: ='Hypothèses Clés'!J9*'Hypothèses Clés'!J15*12 -> 121459.5 | E6: ='Hypothèses Clés'!M9*'Hypothèses Clés'!M15*12 -> 182189.25 | F6: ='Hypothèses Clés'!P9*'Hypothèses Clés'!P15*12 -> 273283.88
A7: Ventes contenu / an | B7: ='Hypothèses Clés'!D7*'Hypothèses Clés'!D22*'Hypothèses Clés'!D16*'Hypothèses Clés'!D19*12 -> 276480 | C7: ='Hypothèses Clés'!G7*'Hypothèses Clés'!G22*'Hypothèses Clés'!G16*'Hypothèses Clés'!G19*12 -> 387072 | D7: ='Hypothèses Clés'!J7*'Hypothèses Clés'!J22*'Hypothèses Clés'!J16*'Hypothèses Clés'!J19*12 -> 541900.8 | E7: ='Hypothèses Clés'!M7*'Hypothèses Clés'!M22*'Hypothèses Clés'!M16*'Hypothèses Clés'!M19*12 -> 758661.12 | F7: ='Hypothèses Clés'!P7*'Hypothèses Clés'!P22*'Hypothèses Clés'!P16*'Hypothèses Clés'!P19*12 -> 1062125.6
A8: Abonnement contenu / an | B8: ='Hypothèses Clés'!D7*'Hypothèses Clés'!D23*'Hypothèses Clés'!D17*'Hypothèses Clés'!D20*12 -> 207129.6 | C8: ='Hypothèses Clés'!G7*'Hypothèses Clés'!G23*'Hypothèses Clés'!G17*'Hypothèses Clés'!G20*12 -> 289981.44 | D8: ='Hypothèses Clés'!J7*'Hypothèses Clés'!J23*'Hypothèses Clés'!J17*'Hypothèses Clés'!J20*12 -> 405974.02 | E8: ='Hypothèses Clés'!M7*'Hypothèses Clés'!M23*'Hypothèses Clés'!M17*'Hypothèses Clés'!M20*12 -> 568363.62 | F8: ='Hypothèses Clés'!P7*'Hypothèses Clés'!P23*'Hypothèses Clés'!P17*'Hypothèses Clés'!P20*12 -> 795709.07
A9: TOTAL REVENUS par mois TTC | B9: =(B4+B5+B6+B7+B8)/12/1.2 -> 50128.75 | C9: =(C4+C5+C6+C7+C8)/12/1.2 -> 70555.125 | D9: =(D4+D5+D6+D7+D8)/12/1.2 -> 99339.488 | E9: =(E4+E5+E6+E7+E8)/12/1.2 -> 139918.75 | F9: =(F4+F5+F6+F7+F8)/12/1.2 -> 197151.45
A10: TOTAL REVENUS par année TTC (TVA 20%) | B10: =SUM(B3:B8)/1.2 -> 601545 | C10: =SUM(C3:C8)/1.2 -> 846661.5 | D10: =SUM(D3:D8)/1.2 -> 1192073.9 | E10: =SUM(E3:E8)/1.2 -> 1679025 | F10: =SUM(F3:F8)/1.2 -> 2365817.5
A12: CHARGES
A13: Charges opérationnelles | B13: ='Charges Opérationnelles'!B17 -> 58747.75 | C13: ='Charges Opérationnelles'!C17 -> 53537.125 | D13: ='Charges Opérationnelles'!D17 -> 64007.594 | E13: ='Charges Opérationnelles'!E17 -> 77016.93 | F13: ='Charges Opérationnelles'!F17 -> 93199.85
A14: Charges Stripe (2€/user) | B14: =('Hypothèses Clés'!C6+'Hypothèses Clés'!C9)*2*12 -> 14400 | C14: =('Hypothèses Clés'!F6+'Hypothèses Clés'!F9)*2*12 -> 18120 | D14: =('Hypothèses Clés'!I6+'Hypothèses Clés'!I9)*2*12 -> 22806 | E14: =('Hypothèses Clés'!L6+'Hypothèses Clés'!L9)*2*12 -> 28710.3 | F14: =('Hypothèses Clés'!O6+'Hypothèses Clés'!O9)*2*12 -> 36151.515
A15: TOTAL CHARGES | B15: =SUM(B13:B14) -> 73147.75 | C15: =SUM(C13:C14) -> 71657.125 | D15: =SUM(D13:D14) -> 86813.594 | E15: =SUM(E13:E14) -> 105727.23 | F15: =SUM(F13:F14) -> 129351.36
A17: EBITDA | B17: =B10-B15 -> 528397.25 | C17: =C10-C15 -> 775004.38 | D17: =D10-D15 -> 1105260.3 | E17: =E10-E15 -> 1573297.8 | F17: =F10-F15 -> 2236466.1
A18: Marge EBITDA (%) | B18: =(B17/B10)*100 -> 87.84002 | C18: =(C17/C10)*100 -> 91.536508 | D18: =(D17/D10)*100 -> 92.717432 | E18: =(E17/E10)*100 -> 93.703058 | F18: =(F17/F10)*100 -> 94.532488
A19: Amortissements | B19: 1500 | C19: 2000 | D19: 2500 | E19: 3000 | F19: 3500
A20: EBIT | B20: =B10-B15-B19 -> 526897.25 | C20: =C10-C13-C19 -> 791124.38 | D20: =D10-D13-D19 -> 1125566.3 | E20: =E10-E13-E19 -> 1599008.1 | F20: =F10-F13-F19 -> 2269117.6
A22: Intérêts financiers | B22: 0 | C22: =E35 -> 14700 | D22: =E36 -> 14160 | E22: =E37 -> 13620 | F22: =E38 -> 13080
A23: Résultat avant impôt | B23: =B10-B15-B19-B22 -> 526897.25 | C23: =C10-C15-C19-C22 -> 758304.38 | D23: =D10-D15-D19-D22 -> 1088600.3 | E23: =E10-E15-E19-E22 -> 1556677.8 | F23: =F10-F15-F19-F22 -> 2219886.1
A24: Impôt (25%) | B24: =B23*0.25 -> 131724.31 | C24: =C23*0.25 -> 189576.09 | D24: =D23*0.25 -> 272150.06 | E24: =E23*0.25 -> 389169.45 | F24: =F23*0.25 -> 554971.52
A25: RESULTAT NET | B25: =B23-B24 -> 395172.94 | C25: =C23-C24 -> 568728.28 | D25: =D23-D24 -> 816450.19 | E25: =E23-E24 -> 1167508.3 | F25: =F23-F24 -> 1664914.6
A26: Marge nette (%) | B26: =(B25/B10)*100 -> 65.692997 | C26: =(C25/C10)*100 -> 67.173042 | D26: =(D25/D10)*100 -> 68.4899 | E26: =(E25/E10)*100 -> 69.534898 | F26: =(F25/F10)*100 -> 70.373755
A30: Montant emprunté | B30: 60000
A31: Taux d'emprunt | B31: 0.045
A32: Nombre d'année de remboursement | B32: 5
A34: Année | B34: Capital remboursé (€) | C34: Intérêts (%) | D34: Intérêts (€) | E34: Annuité | F34: Solde restant
A35: 1 | B35: =B30/B32 -> 12000 | C35: 0.045 | D35: =B30*B31 -> 2700 | E35: =B35+D35 -> 14700 | F35: =B30-B35 -> 48000
A36: 2 | B36: =B30/B32 -> 12000 | C36: 0.045 | D36: =F35*C36 -> 2160 | E36: =B36+D36 -> 14160 | F36: =F35-B36 -> 36000
A37: 3 | B37: =B30/B32 -> 12000 | C37: 0.045 | D37: =F36*C37 -> 1620 | E37: =B37+D37 -> 13620 | F37: =F36-B37 -> 24000
A38: 4 | B38: 12000 | C38: 0.045 | D38: =F37*C38 -> 1080 | E38: =B38+D38 -> 13080 | F38: =F37-B38 -> 12000
A39: 5 | B39: 12000 | C39: 0.045 | D39: =F38*C39 -> 540 | E39: =B39+D39 -> 12540 | F39: =F38-B39 -> 0
